livekit/plugins/gladia/__init__.py
livekit/plugins/gladia/_utils.py
livekit/plugins/gladia/log.py
livekit/plugins/gladia/models.py
livekit/plugins/gladia/py.typed
livekit/plugins/gladia/stt.py
livekit/plugins/gladia/version.py
livekit_plugins_gladia-1.3.11.dist-info/METADATA
livekit_plugins_gladia-1.3.11.dist-info/WHEEL
livekit_plugins_gladia-1.3.11.dist-info/RECORD
